{
    "title": "통계 분석",
    "questions": [
        {
            "number": 1,
            "question": "만족도를 1~5점으로 조사하는 설문에서 사용할 수 있는 척도로 옳은 것은?",
            "passage": null,
            "options": [
                "서열척도",
                "등간척도",
                "명목척도",
                "비율척도"
            ],
            "answer": "1",
            "explanation": "만족도 1~5에 대해 1의 빈도수, 5의 빈도수 등 순서에 의미를 부여하면 서열척도로 볼 수 있고, 1~5점까지 점수를 합산하여 평균을 구하면 일정한 간격을 가진 등간척도로 볼 수 있다"
        },
        {
            "number": 2,
            "question": "아래 보기에서 설명하는 확률적 표본추출 방법으로 옳은 것은?",
            "passage": "모집단의 모든 원소들에게 1, 2, 3...N의 일련번호를 부여하고 이를 순서대로 나열한 후에 일정 간격의 구간으로 나눈다. 첫 구간에서 하나를 임의로 선택한 후에 K째에 위치해 뽑히지 않은 표본을 추출한다.",
            "options": [
                "계통표본추출법",
                "집락표본추출법",
                "단순무작위표본추출법",
                "층화확률표본추출법"
            ],
            "answer": "1",
            "explanation": "계통표본추출법은 모집단의 추출틀에서 K번째 간격마다 하나씩 표본으로 추출하는 방법이다."
        },
        {
            "number": 3,
            "question": "표본조사에 대한 설명으로 옳지 않은 것은?",
            "passage": null,
            "options": [
                "조사과정에서 발생하는 오류는 표본추출오류와 비표본추출오류로 분류된다.",
                "표본편의(Sampling Bias)는 표본추출방법에서 기인하는 오차를 의미한다.",
                "표본오류는 확률화(Randomization)에 의해 최소화하거나 없앨 수 있다.",
                "표본오차와 비표본오차 모두 표본크기가 증가함에 따라 감소한다."
            ],
            "answer": "4",
            "explanation": "표본오차는 표본의 크기가 증가하면 표본집단이 모집단을 더 정확히 반영하게 되어 줄어들지 만 비표본오차는 조사대상자로부터 자료를 수집하는 과정에서 발생되는 측정오차로 표본의 크 기가 증가하더라도 감소하지 않는다."
        },
        {
            "number": 4,
            "question": "시간의 관점에서 A라는 사건이 일어난 이후에 B라는 사건이 발생할 확률을 조건부확률이라고 한다. 아래 빈칸에 들어갈 수식으로 알맞은 것은?",
            "passage": "P(B|A) = (    ) / P(A), 단 P(A) > 0",
            "options": [
                "P(A ∩ B)",
                "P(A)",
                "P(B)",
                "P(A ∪ B)"
            ],
            "answer": "1",
            "explanation": "조건부학률의 정의는 P(B|A) = P(A⋂B)/P(A) 와 같으며, 표본공간 S에서 정의되는 두 사건 A, B에 대하여 동시에 일어날 확률은 교집합이며, 각각이 일어날 확률의 곱으로 정의된다."
        },
        {
            "number": 5,
            "question": "다음 중 아래의 표가 나타내는 확률질량함수를 가진 확률변수 X의 기대값 E(X)로 옳은 것은?",
            "passage": "X     1     2     3\nf(x) 1/6  3/6  2/6",
            "options": [
                "13/6",
                "4/6",
                "2",
                "1"
            ],
            "answer": "1",
            "explanation": "이산형확률변수는 셀 수 있는 정수를 확률을 갖는 변수로 확률변수 x의 기대값은 E(X)=∑xf(x)로 산출한다"
        },
        {
            "number": 6,
            "question": "모집단의 특성을 모수라고 한다. 모수를 추론하기 위해 구하는 표본집단의 특성값으로 옳은 것은?",
            "passage": null,
            "options": [
                "표본통계량",
                "추정치",
                "표본평균",
                "표준오차"
            ],
            "answer": "1",
            "explanation": "표본 관측치의 요약값(계산된 모든 값) 혹은 표본을 요약/설명해주는 기술통계도구를 표본통 계량이라고 한다."
        },
        {
            "number": 7,
            "question": "다음 중 확률 및 확률분포에 대한 설명 중 옳지 않은 것은?",
            "passage": null,
            "options": [
                "모든 사건의 확률은 0과 1 사이에 있다.",
                "서로 배반 사건들의 교집합은 공집합이다.",
                "두 사건 A, B가 독립이라면 사건 B의 확률은 A가 일어난다는 가정하에서의 B의 조건부확률과 같다.",
                "확률분포는 X가 구간 또는 구간들의 모임인 숫자값을 갖는 확률분포함수를 이산형 확률 밀도함수라 한다."
            ],
            "answer": "4",
            "explanation": "확률(Probability)은 어떤 일이 발생할 가능성(경우의 수)의 척도를 의미하며, 어떤 사건이 발 생할 가능성을 0과 1사이의 숫자 혹은 0% ~ 100%의 비율로 표현한 값이다"
        },
        {
            "number": 8,
            "question": "연속확률분포 중 두 집단의 분산을 비교할 때 사용되는 확률분포로 옳은 것은?",
            "passage": null,
            "options": [
                "t 분포",
                "F 분포",
                "χ² 분포",
                "정규분포"
            ],
            "answer": "2",
            "explanation": "두 집단의 분산을 비교할 때 사용되는 확률분포는 F분포이며, 한 집단의 분산을 비교할 때는 x² 분포를 사용한다."
        },
        {
            "number": 9,
            "question": "다음 중 이산확률분포 또는 연속확률분포로 옳지 않은 것은?",
            "passage": null,
            "options": [
                "이항분포",
                "포아송분포",
                "기하분포",
                "감마분포"
            ],
            "answer": "4",
            "explanation": "이산확률분포(이산형확률분포)의 종류는 베르누이분포, 이항분포, 포아송분포, 기하분포 등이 있으며, 연속확률분포(연속형확률분포)에는 표준정규분포, t분포, 감마분포, x²분포, F분포가 있다."
        },
        {
            "number": 10,
            "question": "다음의 chickwts 데이터는 71마리의 병아리들에게 서로 다른 첨가물 종류(feed)를 6주 동안 먹인 후 무게(weight)를 측정한 자료이다. 첨가물의 그릇 간 평균 무게 차이가 있는지에 대한 아래의 분산분석 결과를 해석한 것으로 옳지 않은 것은?",
            "passage": "summary(aov(weight~feed, chickwts))\nDf Sum Sq Mean Sq F value Pr(>F)\nfeed 5 231129 46226 15.37 5.94e-10 ***\nResiduals 65 195556 3009\nSignif. codes: 0 ‘***’ 0.001 ‘**’ 0.01 ‘*’ 0.05 ‘.’ 0.1 ‘ ’ 1",
            "options": [
                "유의수준 0.05에서 첨가물 그룹 간의 무게 평균이 동일하지 않다는 통계적으로 유의한 증거가 있다.",
                "첨가물의 개수는 5개이다.",
                "귀무가설은 '첨가물 그룹 간의 평균이 모두 동일하다' 이다.",
                "위의 가설검정은 통계량을 기반으로 한다."
            ],
            "answer": "2",
            "explanation": "분산분석에서 그룹의 자유도(Df)는 그룹 간 차이를 검정하기 위해 사용되며, 그룹의 수에서 1 을 뺀 값이다"
        },
        {
            "number": 11,
            "question": "추론통계의 신뢰구간에 대한 설명으로 옳지 않은 것은?",
            "passage": null,
            "options": [
                "99% 신뢰구간이 95% 신뢰구간보다 길다.",
                "관측지의 크기가 커지면 신뢰구간의 길이는 줄어든다.",
                "95% 신뢰구간은 미지의 수가 포함되지 않을 확률이 95%를 의미한다.",
                "점추정의 정확성을 보완하는 방법이다."
            ],
            "answer": "3",
            "explanation": "신뢰구간은 점추정의 오차가 달라지는 문제를 보완한 방법이며, 특정확률을 가지고 모집단의 모수가 포함될 것으로 예견되는 구간을 표본으로부터 도출한 범위의 값이다"
        },
        {
            "number": 12,
            "question": "9명의 다이어트 프로그램을 실시하기 전과 후의 체중(kg)을 측정한 결과로 95% 신뢰구간을 설정하고자 할 때 아래 빈 칸 a, b, c에 들어갈 값으로 옳은 것은?",
            "passage": "전 후 d_i = x_1i - x_2i\n1 110 94 16\n2 88 82 6\n3 84 82 2\n4 95 87 8\n5 108 97 11\n6 82 77 5\n7 98 89 9\n8 97 89 8\n9 134 110 24\n\nd = 10, s_d = 8.4, 10 ± t_(a)_(b)x(8.4/√(c))",
            "options": [
                "a = 8, b = 0.025, c = 9",
                "a = 9, b = 0.025, c = 9",
                "a = 8, b = 0.5, c = 8",
                "a = 9, b = 0.5, c = 8"
            ],
            "answer": "1"
        },
        {
            "number": 13,
            "question": "통계적 가설검정에 대한 설명으로 옳지 않은 것은?",
            "passage": null,
            "options": [
                "유의수준은 표본을 추출하여 모평균에 대한 구간추정을 할 때 발생되는 오차의 허용범위이다.",
                "기각역이란 귀무가설이 옳다는 전체하에 구한 검정통계량의 분포에서 확률이 유의수준 크기에 해당하는 값을 의미한다.",
                "P값(유의확률)이 미리 정해 놓은 유의수준(α) 값보다 클 경우, 귀무가설을 기각하고 대립가설의 가정이 옳다고 할 수 있다.",
                "귀무가설이 옳은데도 이를 기각하게 되는 오류를 제1종 오류라고 한다"
            ],
            "answer": "3",
            "explanation": "P값(유의확률)은 측정된 검정통계량의 값으로 계산된 확률로서 귀무가설을 기각하게 하는 최 저의 유의수준이다(검정통계량의 값이 유의하게 되는 최저 유의수준) P값이 유의수준보다 클 경우 귀무가설을 채택한다."
        },
        {
            "number": 14,
            "question": "다음 중 제1종 오류에 대한 설명 중 옳은 것은?",
            "passage": null,
            "options": [
                "귀무가설이 사실일 때, 귀무가설을 사실이라고 판정",
                "귀무가설이 사실 아닐 때, 귀무가설을 사실이라고 판정",
                "귀무가설이 사실일 때, 귀무가설을 사실이 아니라고 판정",
                "귀무가설이 사실 아닐 때, 귀무가설을 사실이 아니라고 판정"
            ],
            "answer": "3",
            "explanation": "귀무가설이 실제로는 사실임에도 허위라고 결론을 내리는 오류를 제1종오류라 한다."
        },
        {
            "number": 15,
            "question": "모수통계 기반 검정방법 중 두 변수중 집단의 평균차이 검정방법으로 옳은 것은?",
            "passage": null,
            "options": [
                "t검정",
                "분산분석",
                "카이스퀘어검정",
                "회귀분석"
            ],
            "answer": "1",
            "explanation": "모수기반 통계기법 중 두 범주형 집단의 평균차이 검정방법은 t검정과 Z검정이 있다"
        },
        {
            "number": 16,
            "question": "중속표본 비모수검정방법 중 단일표본에 대하여 중앙값을 검정하거나 대응표본의 중앙값의 차이가 있는지를 검정하는 방법으로 옳은 것은?",
            "passage": null,
            "options": [
                "부호검정(Sign-Test)",
                "맨휘트니U검정",
                "카이제곱검정",
                "크루스칼왈리스검정"
            ],
            "answer": "1",
            "explanation": "비모수검정 중 단일표본에 대하여 중앙값을 검정하거나 대응표본의 중앙값의 차이가 있는지를 검정하는 방법은 부호검정(Sign-Test)과 월슨부호순위검정(Wilcoxon Signed Rank test) 이 있다."
        },
        {
            "number": 17,
            "question": "기초통계량의 단위인 중심경향치와 산포도에 대한 설명으로 옳지 않은 것은?",
            "passage": null,
            "options": [
                "중앙값은 대표적인 중심경향치로 평균값보다 이상치 및 다른 관찰값에 대해 민감하다는 단점이 있다.",
                "최빈값은 자료에서 빈도수가 가장 많은 값을 의미하며 평균과 달리 소수의 극단치에 영향을 받지 않는다.",
                "평균은 모든 관측값을 더한 값을 관측값의 갯수(n)로 나눈 값을 의미한다.",
                "사분위수 범위는 데이터 값들을 상위 50%에 포함되는 산포도를 의미한다."
            ],
            "answer": "1",
            "explanation": "중앙값은 대표적인 중심경향치로 평균보다 이상값 및 다른 관측값에 대해 덜 민감하다는 장점 이 있다."
        },
        {
            "number": 18,
            "question": "비대칭성 정도를 나타내는 통계량인 왜도에서 오른쪽으로 긴 꼬리를 갖는 분포의 최빈값, 중앙값, 평균의 크기 순서로 옳은 것은?",
            "passage": null,
            "options": [
                "최빈값 < 중앙값 < 평균값",
                "중앙값 < 최빈값 < 평균값",
                "평균값 < 최빈값 < 중앙값",
                "최빈값 < 평균값 < 중앙값"
            ],
            "answer": "1",
            "explanation": "오른쪽으로 긴 꼬리를 갖는 분포(Right Skewed)는 왜도는 0보다 크며, 최빈값 〈 중앙값 〈 평균 순으로 값이 정해진다."
        },
        {
            "number": 19,
            "question": "다음 히스토그램에서 집단 간 차이를 가장 잘 드러내는 통계량으로 가장 적절한 것은 무엇인가?",
            "passage": "./exams/day6/19.png",
            "options": [
                "평균",
                "사분위수 범위",
                "최빈값",
                "중앙값"
            ],
            "answer": "2",
            "explanation": "집단 간 차이는 산포도로 확인할 수 있으며, 산포도를 확인할 수 있는 통계량은 분산, 표준편차, 사분위수 범위가 있다"
        },
        {
            "number": 20,
            "question": "통계적 추론방법인 추정에 대한 설명으로 옳지 않은 것은?",
            "passage": null,
            "options": [
                "추정은 통계량을 이용하여 모집단의 모수의 근사값을 결정하는 방법을 의미한다.",
                "표본크기가 커질수록 신뢰구간이 줄어지긴다. 이는 정보가 많을수록 추정값이 더 정밀하다는 것을 의미한다.",
                "신뢰수준 95%의 의미는 추정값이 신뢰구간에 존재할 확률이 95%라고 할 수 있다.",
                "점추정은 표본자료를 이용하여 모수의 참값이라고 추정하기 위한 하나의 값을 결정하는 방법이다."
            ],
            "answer": "3",
            "explanation": "점추정은 표본자료를 이용하여 모수의 참값이라고 추정되는 하나의 값을 결정하는 통계적 추 정 방법이며, 표본이 커질수록 신뢰구간은 좁아진다"
        },
        {
            "number": 21,
            "question": "다음은 Carseats 데이터의 상관계수 및 summary 함수 결과에 대한 해석이다. 분석결과에 대한 해석으로 옳지 않은 것은?",
            "passage": "summary(Carseats)\nSales   CompPrice  Income Advertising Population Price ShelveLoc Age Education Urban US\nMin. : 0.000 Min.   : 77 Min.  : 21.00 Min. : 0.000 Min.  : 10.0 Min.  : 24.0 Bad : 96 Min.  :25.00 Min. :10.0 No :118 No :142\n1st Qu.: 5.390 1st Qu.:115 1st Qu.: 42.75 1st Qu.: 0.000 1st Qu.:139.0 1st Qu.:100.0 Medium:219 1st Qu.:35.00 1st Qu.:12.0 Yes:282 Yes:258\nMedian : 7.490 Median :125 Median : 69.00 Median : 6.000 Median :264.0 Median :117.0 Good :185 Median :54.50 Median :14.0\nMean   : 7.496 Mean   :125 Mean   : 68.66 Mean   : 6.635 Mean   :264.8 Mean   :115.8 Mean : 54.49 Mean   :13.9\n3rd Qu.: 9.320 3rd Qu.:135 3rd Qu.: 89.00 3rd Qu.:12.000 3rd Qu.:398.5 3rd Qu.:131.0 3rd Qu.:70.00 3rd Qu.:16.0\nMax.   :16.270 Max.   :175 Max.   :120.00 Max.   :29.000 Max.   :509.0 Max.   :191.0 Max.   :80.00 Max.   :18.0",
            "options": [
                "US변수는 구간척도(등간척도)에 해당한다.",
                "ShelveLoc는 Good인 카시트의 비율이 0.21이다.",
                "ShelveLoc는 명목척도에 해당한다.",
                "US변수가 No인 카시트가 Yes인 카시트보다 작다."
            ],
            "answer": "1",
            "explanation": "summary() 함수는 주어진 데이터에 대한 기초 통계를 요약하여 출력해주는 함수이며, 연속 형 변수는 평균, 사분위수, 최소/최대값을 출력하며, 범주형 변수는 범주의 빈도수를 계산해 준다"
        },
        {
            "number": 22,
            "question": "다음 중 Lasso 회귀모델에 대한 설명으로 옳지 않은 것은?",
            "passage": null,
            "options": [
                "모형에 포함된 회귀계수들의 절대값의 크기가 클수록 penalty를 부여하는 방식이다.",
                "L2 penalty를 사용한다.",
                "선택과정으로 penalty의 정도를 조정한다.",
                "자동적으로 변수 선택을 하는 효과가 있다."
            ],
            "answer": "2",
            "explanation": "라쏘(Lasso) 회귀는 모델의 설명력에 기여하지 못하는 독립변수의 회귀계수를 0으로 만드는 방법이며 페널티로 절대값(L1-norm)을 사용한다."
        },
        {
            "number": 23,
            "question": "다음은 Orange 나무의 종류, 연령, 둘레에 관한 데이터의 분석결과이다. 분석결과에 대한 해석으로 옳지 않은 것은?",
            "passage": "summary(Orange)\nTree      age        circumference\n3:7   Min.   : 118.0   Min.   : 30.0\n1:7   1st Qu.: 484.0   1st Qu.: 65.5\n5:7   Median :1004.0   Median :115.0\n2:7   Mean   : 922.1   Mean   :115.9\n4:7   3rd Qu.:1372.0   3rd Qu.:161.5\n      Max.   :1582.0   Max.   :214.0\nboxplot(circumference~Tree, Orange)",
            "options": [
                "age 변수의 최대값은 1582.0이다.",
                "4의 Tree의 중위수가 가장 크다.",
                "Tree는 연속형 변수이다.",
                "orange dataset은 결측값이 존재하지 않는다."
            ],
            "answer": "3",
            "explanation": "Tree 변수의 범주는 각 7개의 데이터가 3, 1, 5, 2, 4 범주로 구분된다"
        },
        {
            "number": 24,
            "question": "목표변수(종속변수)가 연속형일 회귀나무에서 분류 기준값의 선택방법으로 옳은 것은?",
            "passage": null,
            "options": [
                "카이제곱통계량, 지니지수",
                "지니지수, 엔트로피지수",
                "엔트로피지수, 분산감소량",
                "분산감소량, F-통계량"
            ],
            "answer": "4",
            "explanation": "분류나무의 분리기준은 카이제곱통계량, 지니지수, 엔트로피지수가 있고, 회귀나무의 분리기 준은 분산감소량과 F통계량의 p값이 있다."
        },
        {
            "number": 25,
            "question": "다음은 USArrests데이터의 주성분분석 결과인 R 스크립트이다. 80% 이상의 자료를 설명하려고 할 때 필요한 주성분의 최소 갯수로 옳은 것은?",
            "passage": "fit<-princomp(USArrests, cor=TRUE)\nsummary(fit)\nImportance of components: Comp.1 Comp.2 Comp.3 Comp.4\nStandard deviation 1.5748783 0.9948694 0.5971291 0.41644938\nProportion of Variance 0.6200604 0.24670871 0.0891408 0.0435752\nCumulative Proportion 0.6200604 0.8676071 0.9567479 1.0000000",
            "options": [
                "1개",
                "2개",
                "3개",
                "4개"
            ],
            "answer": "2",
            "explanation": "주성분분석에서 주성분의 갯수는 누적기여율(Cumulative Proportion)이 85% 이상에 해당하 는 주성분의 수로 결정하게 된다"
        },
        {
            "number": 26,
            "question": "다음은 다중 로지스틱회귀분석 결과이다. 분석결과에 대한 해석으로 옳지 않은 것은?",
            "passage": "Call:\nglm(formula = default ~., family = binomial, data = Default)\n\nDeviance Residuals:\nMin      1Q  Median      3Q     Max\n-2.4691 -0.1418 -0.0557 -0.0203  3.7383\n\nCoefficients:\n            Estimate Std. Error z value Pr(>|z|)\n(Intercept) -1.087e+01  4.923e-01 -22.080  < 2e-16 ***\nstudentYes  -6.468e-01  2.363e-01  -2.738  0.00619 **\nbalance      5.737e-03  2.319e-04  24.738  < 2e-16 ***\nincome       3.033e-06  8.203e-06   0.370  0.71152\n---\nSignif. codes: 0 ‘***’ 0.001 ‘**’ 0.01 ‘*’ 0.05 ‘.’ 0.1 ‘ ’ 1\n\n(Dispersion parameter for binomial family taken to be 1)\n\nNull deviance: 2926.6  on 9999  degrees of freedom\nResidual deviance: 1571.5  on 9996  degrees of freedom\nAIC: 1579.5\n\nNumber of Fisher Scoring iterations: 8",
            "options": [
                "studentYes일 때 채무불이행(default)이 될 확률이 적다.",
                "로지스틱회귀분석은 지도학습에 해당된다.",
                "income은 default에 통계적으로 유의미한 영향을 주는 변수이다.",
                "balance는 채무불이행(default)에 통계적으로 유의미한 영향을 주는 변수이다."
            ],
            "answer": "3",
            "explanation": "로지스틱회귀분석은 지도하습 중 분류기법에 해당하며, 주어진 결과로 보아 StudentYes 회 귀계수(Estimate)가 -6.468e-01인 것으로 보아 Yes일 때 Default가 Yes일 확률이 낮다"
        },
        {
            "number": 27,
            "question": "변수 선택 기준으로 사용하는 통계량에 대한 설명 중 옳지 않은 것은?",
            "passage": null,
            "options": [
                "AIC, BIC를 최소화한다는 뜻은 우도(Likelihood)를 가장 크게 하는 동시에 변수 개수는 가장 적은 최적의 모형(Parsimonious & Explainable)을 의미하게 된다.",
                "BIC는 AIC와 달리 변수의 개수에 대한 패널티를 더 크게 부여한다.",
                "AIC, BIC는 통계량이 낮을수록 적합한 변수를 선택 조합하게 판단할 수 있다.",
                "AIC는 BIC가 과적합이 되는 경향을 제어하기 위해 사용한다."
            ],
            "answer": "4",
            "explanation": "AIC와 BIC는 변수 선택 기준 척도로써 활용되며, 각 통계량이 낮을수록 적합한 변수 선택의 조합임을 나타낸다"
        },
        {
            "number": 28,
            "question": "다음 중 비모수검정의 특징으로 옳지 않은 것은?",
            "passage": null,
            "options": [
                "절대적인 크기가 중요하므로 표본평균, 표본분산 등을 이용해 검정을 실시한다.",
                "측준에서 제시된 모수적 방법보다 훨씬 단순하다.",
                "통계에 부합 좋은 측 수에 의해 계산되므로 이상값(outlier)에 영향을 적게 받는다.",
                "비모수검정은 모수 지제분는 분포형태에 관한 검정을 실시한다."
            ],
            "answer": "1",
            "explanation": "비모수통계는 모집단이 정규성을 가정하지 않으며(모집단이 정규분포를 따른다는 가정이 없음), 표본수 10개 미만인 경우 사용할 수 있다"
        },
        {
            "number": 29,
            "question": "아래의 그래프에서 위배되고 있는 회귀모델의 가정사항으로 옳은 것은?",
            "passage": "./exams/day6/29.png",
            "options": [
                "선형성",
                "정규성",
                "등분산성",
                "독립성"
            ],
            "answer": "3",
            "explanation": "동분산성은 오치의 분산이 독립변수값과 무관하게 일정해야 한다는 가정이며, 아무런 관련성이 없게 점들이 무작위적으로 고르게 분포되어야 등분산성을 만족한다고 볼 수 있다."
        },
        {
            "number": 30,
            "question": "선형회귀모델의 오차항에 대한 가정조건으로 옳은 것은?",
            "passage": null,
            "options": [
                "독립성, 선형성, 등분산성",
                "독립성, 등분산성, 정규성",
                "정규성, 효율성, 등분산성",
                "정규성, 편성, 독립성"
            ],
            "answer": "2",
            "explanation": "회귀분석의 가정사항 중 오차항에 대한 가정은 오차의 독립성, 오차의 정규성, 등분산성이며, 선형성은 독립변수와 종속변수의 특성을 의미한다."
        },
        {
            "number": 31,
            "question": "회귀모델의 잔차분석에 대한 설명 중 옳지 않은 것은?",
            "passage": null,
            "options": [
                "잔차분석은 회귀모델에 대한 가정(정규성, 등분산성, 독립성)을 충족하는지 또는 이상 값이 개입하는지에 대한 검정절차이다.",
                "잔차항이 정규분포를 따르는지 알아보는 검정으로 샤피로월크(Shapiro-Wik)가 있다.",
                "잔차가 특정한 패턴을 가진다면 모델(설명되는 부분)에 추가해야 할 요소가 남아 있음을 의미한다. 따라서 잔차는 특정한 패턴이 없어야 한다.",
                "더빈왓슨(Durbin-Watson) 검정은 대표적인 등분산성에 대한 검정기법이다."
            ],
            "answer": "4",
            "explanation": "잔차분석은 회귀모델에 대한 가정(정규성, 등분산성, 독립성)을 충족하는지 또는 이상값이 개 입하는지에 대한 검정 절차이며, 등분산성의 만족 여부는 레빈의 검정(Levene's test)과 바틀렛 검정(Bartlett's test) 등을 이용한다"
        },
        {
            "number": 33,
            "question": "다음은 Wage 데이터의 t검정 결과에 대한 해석이다. 분석결과에 대한 해석으로 옳지 않은 것은?",
            "passage": "> data(\"Wage\")\n> t.test(Wage$wage, mu=100)\n\nOne Sample t-test\n\ndata:  Wage$wage\nt = 15.362, df = 2999, p-value < 2.2e-16\nalternative hypothesis: true mean is not equal to 100\n95 percent confidence interval: 110.2098 113.1974\nsample estimates:\nmean of x  111.7036",
            "options": [
                "한 집단의 평균에 대한 t검정 결과이다.",
                "평균에 대한 95% 신뢰구간은 귀무가설에서 설정한 평균의 참값을 포함한다.",
                "양측검정 결과를 보여주고 있다.",
                "t검정의 자유도는 2999이다."
            ],
            "answer": "2",
            "explanation": "제시된 코드는 급여(wage) 평균이 100이라고 귀무가설을 설정하고 이를 검정하기 위한 일표 본 t검정에 대한 문제이다"
        },
        {
            "number": 35,
            "question": "회귀분석의 영향력 진단에 대한 설명 중 가장 적절하지 않은 것은?",
            "passage": null,
            "options": [
                "Cook's Distance가 기준값인 1보다 클 경우 영향치로 간주한다.",
                "DFBETAS(Difference in betas)는 해당 관측값의 개별 베타값에 대한 영향력 지표이다.",
                "적합값(Fitted Value)에 대한 영향력은 DFFITS(difference in Standardized Fits)로 기준값보다 작을수록 영향력을 가능성이 높다.",
                "Leverage Hi는 관측치가 다른 관측치 집단으로부터 떨어진 정도를 의미한다."
            ],
            "answer": "3",
            "explanation": "DFFITS(difference in Standardized Fits)는 모든 관측치를 활용하여 추정된 회귀모델 예측 값과 해당 관측값을 제외한 후 추정된 회귀모델의 예측값 변화 정도를 측정하는 방법이며, 기준값보다 클수록 영향값일 가능성이 높다."
        },
        {
            "number": 36,
            "question": "기술통계에 대한 설명으로 옳지 않은 것은?",
            "passage": null,
            "options": [
                "기술통계(Descriptive statistics)를 하기 위해서는 추론통계(Inferential statistics)가 선행되어야 한다.",
                "조사 및 측정된 자료를 통해 그 자료가 가지고 있는 특징을 수치, 표, 그래프로 정리하는 과정이다.",
                "모수와 표본통계량을 계산해내는 통계학의 한 분야로 평균값, 중앙값, 최빈값, 최대값 등의 통계량을 데이터의 중심경향성과 분포사태를 파악하는 데 활용된다.",
                "데이터 탐색에서 데이터에 대한 충분한 이해를 얻기 위해 데이터의 요약정보를 활용한다."
            ],
            "answer": "1",
            "explanation": "추론통계(Inerential statistics)를 하기 위해 기술통계(Descriptive statistics)가 선행되어야 한다"
        },
        {
            "number": 37,
            "question": "중심극한정리에 대한 설명으로 옳지 않은 것은?",
            "passage": null,
            "options": [
                "모집단의 분포가 정규분포에 가까워져야 표본평균의 분포가 정규분포로 근사하게 된다.",
                "중심극한정리가 성립하기 위해서는 표본크기가 최소 30 이상이어야 한다.",
                "모집단이 정규분포가 아닐 때 서로 다른 표본의 크기에 대한 표본평균의 분포들이 표 본의 크기가 커짐에 따라 정규분포에 가까워지게 된다.",
                "표본크기가 증가할수록 표본평균과 표준편차가 모집단의 평균과 표준편차에 가까워짐을 의미하게 된다."
            ],
            "answer": "1",
            "explanation": "중심극한정리는 정확한 분포가 알려지지 않았거나 다루기 힘든 경우 근사분포를 제공하며, 추 출한 표본의 n이 충분히 크면(일반적으로 n ≥ 30이면) 모집단 분포의 모양에 상관없이 추출된 표본들의 평균의 분포는 표준정규분포 N(0,1)를 따른다는 법칙이다."
        },
        {
            "number": 38,
            "question": "다중회귀분석에서 독립변수들 사이에 선형관계가 존재할 경우 회귀계수의 정확한 추정이 어려워지는 현상으로 알맞은 것은?",
            "passage": null,
            "options": [
                "회귀모델의 적합성 위배",
                "다중공선성",
                "등분산성",
                "회귀계수의 유의성 검정"
            ],
            "answer": "2",
            "explanation": "다중공선성은 회귀분석에서 독립변수들 간에 강한 상관관계가 나타나는 문제이다"
        },
        {
            "number": 39,
            "question": "상관관계 분석에 대한 설명으로 옳지 않은 것은?",
            "passage": null,
            "options": [
                "종속변수에 미치는 영향력의 크기를 파악해 종속변수를 예측하는 선형모델 산출방법이다.",
                "정규성이라는 가정을 충족시켜야 한다.",
                "스피어만의 상관계수로 비선형관계를 확인할 수 있다.",
                "상관계수를 선택하는 기준은 측정하고자 하는 데이터의 형태에 따라 달라진다."
            ],
            "answer": "1",
            "explanation": "상관관계분석의 가정은 두 개의 연속형 변수 존재, 정규성 만족, 선형성 존재이며, 피어슨 상관 계수는 연속형 변수의 선형적 상관관계를 상관계수로 표현하며, 스피어만 상관계수는 두 변수 를 순위를 변환하여 비선형 관계를 파악하게 된다"
        },
        {
            "number": 40,
            "question": "아래 그래프의 상관계수에 대한 설명 중 적절한 것은 무엇인가?",
            "passage": "./exams/day6/40.png",
            "options": [
                "피어슨의 상관계수는 두 계량형 변수(연속형 변수) 또는 순서형 변수 사이의 단순관계 분석지표다.",
                "피어슨 및 스피어만 상관계수의 범위는 다르다.",
                "위의 그래프의 두 변수 간의 관계에서 스피어만의 상관계수는 1이다.",
                "위의 그래프의 두 변수 간의 관계에서 피어슨 상관계수는 1이다."
            ],
            "answer": "3",
            "explanation": "피어슨 상관계수는 연속형 두 변수, 스피어만 상관계수는 서열형 두 변수 간의 상관관계를 분 석하며, 각 상관계수의 범위는 -1~1의 값을 가진다"
        },
        {
            "number": 41,
            "question": "상관계수에 대한 설명 중 옳지 않은 것은?",
            "passage": "./exams/day6/41.png",
            "options": [
                "mpg와 cyl는 음의 상관관계이다.",
                "qsec과 drat는 제일 낮은 상관계수이다.",
                "drat와 hp는 통계적으로 유의하다.",
                "각 독립변수 상호 간의 영향력이 있을 수 있다."
            ],
            "answer": "3",
            "explanation": "상관계수로 변수 간의 선형관계의 유의성을 확인할 수 있지만 통계적 유의성은 상관계수가 아 닌 상관계수를 이용한 통계량을 산출하여 확인할 수 있다"
        },
        {
            "number": 42,
            "question": "데이터 간의 거리를 바탕으로 이들 간의 관계 구조를 시각적으로 표현하는 통계 데이터 분석기법으로 옳은 것은?",
            "passage": null,
            "options": [
                "다차원척도법",
                "SOM",
                "인공신경망",
                "로지스틱회귀분석"
            ],
            "answer": "1",
            "explanation": "다차원척도법(Multidimensional Scaling, MDS)은 데이터 간의 거리(Distance)를 바탕으 로 이들 간의 관계구조를 시각적으로 표현하는 통계 데이터 분석기법이다(개체 간 근접성 : Proximity)"
        },
        {
            "number": 43,
            "question": "두 개의 확률변수 X, Y의 공분산에 대한 설명으로 옳지 않은 것은?",
            "passage": null,
            "options": [
                "공분산이 양수이면 X가 증가할 때 Y도 증가한다.",
                "공분산이 음수이면 X가 증가할 때 Y도 감소한다.",
                "공분산이 0이면 두 변수 간에는 아무런 선형관계가 없으며 두 변수는 서로 독립적인 관계이다.",
                "공분산의 크기는 상관계수와 동일하게 -1~1 사이의 범위를 갖는다."
            ],
            "answer": "4",
            "explanation": "공분산은 두 변수 X, Y가 서로 어떤 패턴(Pattern)을 보여주는가를 나타내는 지표이며, 서로 다른 변수들 사이에 얼마나 의존하는지를 수치적으로 표현하다"
        },
        {
            "number": 44,
            "question": "주성분 수의 결정에 대한 설명 중 옳지 않은 것은?",
            "passage": null,
            "options": [
                "스크리플롯(Scree Plot)을 통해서 주성분의 분산 감소가 급격하게 줄어들어 주성분의 개수를 늘릴 때 얻게 되는 정보의 양이 상대적으로 미미한 점점에서 주성분의 개수를 정할 수 있다.",
                "주성분분석을 설명하는 총 분산의 비율이 70~90% 사이가 되는 주성분의 개수를 선택할 수도 있다.",
                "고유값(Eigen Values)이 평균값 이상이 되도록 주성분을 제거한다.",
                "위의 3가지 방법을 고려하여 주성분의 수를 결정한다."
            ],
            "answer": "3",
            "explanation": "주성분분석에서 주성분의 갯수는 고유값이 1이상이거나 1에 가까운 주성분만 선택(주성분이 설명하는 분산의 양), 누적기여율이 85% 이상에 해당하는 주성분의 수 결정, 스크리플랏(Scree Plot)를 통해 그래프가 완만해지는 부분 이전의 주성분을 선택하는 방법을 사용할 수 있다."
        },
        {
            "number": 45,
            "question": "다음 중 주성분분석(PCA)에서 변수 중요도의 기준이 되는 값으로 옳은 것은?",
            "passage": null,
            "options": [
                "고유값(Eigen Value)",
                "특이값(Singular Value)",
                "판별점수",
                "공분산행렬"
            ],
            "answer": "1",
            "explanation": "주성분분석(PCA)에서 주성분의 갯수는 고유값(설명 가능한 분산), 누적기여율(특정 고유값의 비율), 스크리플랏(Scree Plot)를 통해 설정할 수 있다."
        },
        {
            "number": 46,
            "question": "시계열 데이터를 분석하기 위한 절차로 옳은 것은?",
            "passage": null,
            "options": [
                "시간 그래프 그리기 → 추세와 계절성 제거하기 → 잔차 예측하기 → 잔차에 대한 모델 적합하기 → 예측된 잔차에 추세와 계절성을 더하여 미래 예측하기",
                "추세와 계절성 제거하기 잔차 예측하기 → 잔차에 대한 모델 적합하기 → 예측된 잔차에 추세와 계절성을 더하여 미래 예측하기 → 시간 그래프 그리기",
                "잔차 예측하기 → 잔차에 대한 모델 적합하기 → 예측된 잔차에 추세와 계절성을 더하여 미래 예측하기 → 시간 그래프 그리기 → 추세와 계절성 제거하기",
                "예측된 잔차에 추세와 계절성을 더하여 미래 예측하기 → 간 그래프 그리기 → 추세와 계절성 제거하기 → 잔차 예측하기 → 잔차에 대한 모델 적합하기"
            ],
            "answer": "1",
            "explanation": "시계열 데이터를 분석하기 위한 절차는 시간 그래프 그리기 → 추세와 계절성 제거하기 잔차 예측하기 → 잔차에 대한 모델 적합하기 → 예측된 잔차에 추세와 계절성을 더하여 미래 예측 하기 순으로 수행될 수 있다."
        },
        {
            "number": 47,
            "question": "전통적 시계열분석 기법 중 최근 시계열에 더 많은 가중치를 부여하는 방법으로 옳은 것은?",
            "passage": null,
            "options": [
                "시계열분석법",
                "이동평균법",
                "지수평활법",
                "회귀분석법"
            ],
            "answer": "3",
            "explanation": "지수평활법은 일정기간의 평균을 이용하는 이동평균법과는 달리 모든 시계열 자료를 사용하여 평균을 구한 후 시간의 흐름에 따라 최근 시계열에 더 많은 가중치(지수평활 계수 a)를 부여하 여 미래를 예측하는 방법이다."
        },
        {
            "number": 48,
            "question": "시계열모델에 대한 설명으로 옳지 않은 것은?",
            "passage": null,
            "options": [
                "과거의 자료가 현재 자료에 영향을 주는 모형을 자기회귀모델이라고 한다.",
                "현재 자료로 과거의 백색잡음의 선형결합으로 나타내는 모형을 이동평균모델이라고 한다.",
                "정상성을 만족하지 않는 시계열 자료를 모형화할 수 없다.",
                "계절성을 갖는 비정상시계열은 계절성을 이용해 정상시계열로 바꿀 수 있다."
            ],
            "answer": "3",
            "explanation": "정삼성을 가지지 않는 시계열 자료는 일반적으로 추세, 계절성 등이 포함되어 있어서 시간에 따라서 변화하는 특징을 가지고 있다"
        },
        {
            "number": 49,
            "question": "분해시계열에 대한 설명 중 적절하지 않은 것은?",
            "passage": null,
            "options": [
                "자료가 어떤 특정한 형태를 취할 때 추세요인(Trend Factor)이 있다고 한다.",
                "고정된 주기에 따라 자료가 변화할 경우 계절요인(Seasonal Factor)이 있다고 한다.",
                "순환요인(Cycle Factor)은 경제 전반에나 특정 산업의 원인으로 나타난다.",
                "회귀분석에서의 오차에 해당하는 요인은 불규칙요인(Irregular Factor)라고 한다."
            ],
            "answer": "3",
            "explanation": "시계열분해법(Time Series Decomposition, = 분해시계열)은 시계열 데이터를 추세요인, 순 환요인, 계절요인, 불규칙요인으로 분해하는 기법이며, 순환요인은 특정 주기 혹은 수년 간의 간격으로 발생하는 주기적인 패턴이다."
        },
        {
            "number": 50,
            "question": "ARIMA(자기회귀누적이동평균모델)는 기본적으로 비정상시계열모델이기 때문에 차분이나 변환을 통해 AR, MA, ARMA 모형으로 정상화할 수 있다. ARIMA(1, 2, 3)에서 ARMA로 정상화할 때의 차분한 횟수로 옳은 것은?",
            "passage": null,
            "options": [
                "1",
                "2",
                "3",
                "4"
            ],
            "answer": "2",
            "explanation": "ARIMA(1, 2, 3)에서 I(차분, 즉 통합)는 의미하며, 2의 값이 이에 해당한다"
        }
    ]
}